fair_forge/__init__.py
fair_forge/_metrics_common.py
fair_forge/data/adult.parquet
fair_forge/data/toy.parquet
fair_forge/data_metrics.py
fair_forge/datasets.py
fair_forge/eval.py
fair_forge/methods.py
fair_forge/metrics.py
fair_forge/nn/__init__.py
fair_forge/nn/beutel.py
fair_forge/nn/utils.py
fair_forge/preprocessing/__init__.py
fair_forge/preprocessing/definitions.py
fair_forge/preprocessing/group_pre_method.py
fair_forge/py.typed
fair_forge/split.py
fair_forge/utils.py
fair_forge-0.4.1.dist-info/WHEEL
fair_forge-0.4.1.dist-info/METADATA
fair_forge-0.4.1.dist-info/RECORD
