Metadata-Version: 2.3
Name: fair-forge
Version: 0.4.1
Summary: A toolkit for developing group-aware ML methods
Author: Thomas M Kehrenberg
Author-email: Thomas M Kehrenberg <tmke8@posteo.net>
Requires-Dist: polars>=1.31.0
Requires-Dist: scikit-learn>=1.7.0
Requires-Dist: flax>=0.10.7 ; extra == 'nn'
Requires-Python: >=3.12
Provides-Extra: nn
